schu_auth/__init__.py
schu_auth/auth.py
schu_auth/response.py
SCHU_Auth-1.0.1.dist-info/LICENSE
SCHU_Auth-1.0.1.dist-info/METADATA
SCHU_Auth-1.0.1.dist-info/WHEEL
SCHU_Auth-1.0.1.dist-info/top_level.txt
SCHU_Auth-1.0.1.dist-info/RECORD
